my_history/__init__.py
my_history/cli.py
my_history-0.1.4.dist-info/METADATA
my_history-0.1.4.dist-info/WHEEL
my_history-0.1.4.dist-info/entry_points.txt
my_history-0.1.4.dist-info/top_level.txt
my_history-0.1.4.dist-info/RECORD
