Metadata-Version: 2.1
Name: my_history
Version: 0.1.4
Summary: Default template for PDM package
Author-email: EstherCho-7 <dkgkqm777@gmail.com>
License: MIT
Project-URL: Homepage, https://github.com/EstherCho-7/my_history
Project-URL: Issues, https://github.com/EstherCho-7/my_history/issues
Requires-Python: >=3.9
